cce/__init__.py
cce/estimator.py
cce/optimization.py
cce/preprocessing.py
cce/scoring.py
channel_capacity_estimator-1.1.dist-info/METADATA
channel_capacity_estimator-1.1.dist-info/WHEEL
channel_capacity_estimator-1.1.dist-info/RECORD
