Metadata-Version: 2.1
Name: channel-capacity-estimator
Version: 1.1
Summary: Package for estimation of information channel capacity.
License: GPL-3.0
Author: Frederic Grabowski
Author-email: grabowski.frederic@gmail.com>, Pawel Czyz <pczyz@protonmail.com
Requires-Python: >=3.8,<3.12
Classifier: License :: OSI Approved :: GNU General Public License v3 (GPLv3)
Classifier: Programming Language :: Python :: 3
Classifier: Programming Language :: Python :: 3.8
Classifier: Programming Language :: Python :: 3.9
Classifier: Programming Language :: Python :: 3.10
Classifier: Programming Language :: Python :: 3.11
Requires-Dist: numpy (>=1.12,<2.0)
Requires-Dist: scipy (>=1.0.0,<2.0.0)
Requires-Dist: tensorflow (>=2.2.0)
